LICENSE.txt
README.md
pyproject.toml
setup.py
filament/__init__.py
filament/_choices.py
filament/_constraint.py
filament/_exceptions.py
filament/_export.py
filament/_import.py
filament/_importpath.py
filament/_taggedclass.py
filament/_types.py
filament.egg-info/PKG-INFO
filament.egg-info/SOURCES.txt
filament.egg-info/dependency_links.txt
filament.egg-info/requires.txt
filament.egg-info/top_level.txt